<Namespace Name="Microsoft.Azure.Management.Compute.Fluent.VirtualMachineScaleSetUnmanagedDataDisk.UpdateDefinition">
  <Docs>
    <summary><span data-ttu-id="e29a5-101">仮想マシン スケール セットを更新プログラムの定義をサポートしていますがアンマネージ データ ディスクを使用しているインターフェイスが含まれています。</span><span class="sxs-lookup"><span data-stu-id="e29a5-101">Contains interfaces that supports defining the update the virtual machines in a scale set that are using unmanaged data disks.</span></span></summary> 
    <remarks>To be added.</remarks>
  </Docs>
</Namespace>
